TerminalUI/CustomUrwidWidgets.py
TerminalUI/TerminalUI.py
TerminalUI/__init__.py
terminalui-0.1.3.dist-info/LICENSE.md
terminalui-0.1.3.dist-info/METADATA
terminalui-0.1.3.dist-info/WHEEL
terminalui-0.1.3.dist-info/top_level.txt
terminalui-0.1.3.dist-info/RECORD
