Metadata-Version: 2.1
Name: terminalui
Version: 0.1.3
Summary: A Python Terminal User Interface based on urwid with asynchronous input/output that can be easily expanded to your application.
Home-page: https://github.com/jmount1992/TerminalUI
Author: James Mount
Author-email: jmount1992@gmail.com
License: UNKNOWN
Platform: UNKNOWN
Classifier: Programming Language :: Python :: 3
Classifier: License :: OSI Approved :: MIT License
Classifier: Operating System :: OS Independent
Requires-Python: >=3.6
Requires-Dist: urwid (>=2.1.2)
